[
  {
    "CaseEventID": "directionIssued",
    "CaseFieldID": "prePostHearing",
    "CaseTypeID": "Benefit",
    "DisplayContext": "MANDATORY",
    "LiveFrom": "01/01/2018",
    "PageDisplayOrder": 1,
    "PageFieldDisplayOrder": 1,
    "PageID": "1.0",
    "PageLabel": "Issue direction",
    "ShowSummaryChangeOption": "Y"
  },
  {
    "CallBackURLMidEvent": "${CCD_DEF_TRIBUNALS_API_URL}/ccdMidEvent",
    "CaseEventID": "directionIssued",
    "CaseFieldID": "directionTypeDl",
    "CaseTypeID": "Benefit",
    "DisplayContext": "MANDATORY",
    "LiveFrom": "01/01/2018",
    "PageDisplayOrder": 1,
    "PageFieldDisplayOrder": 2,
    "PageID": "1.0",
    "PageLabel": "Issue direction",
    "ShowSummaryChangeOption": "Y"
  },
  {
    "CaseEventID": "directionIssued",
    "CaseFieldID": "confidentialityType",
    "CaseTypeID": "Benefit",
    "DisplayContext": "MANDATORY",
    "LiveFrom": "01/01/2018",
    "PageDisplayOrder": 1,
    "PageFieldDisplayOrder": 3,
    "PageID": "1.0",
    "PageLabel": "Issue direction"
  },
  {
    "LiveFrom": "06/10/2022",
    "CaseEventID": "directionIssued",
    "CaseFieldID": "hearingRoute",
    "CaseTypeID": "Benefit",
    "DisplayContext": "READONLY",
    "FieldShowCondition": "confidentialityType=\"DUMMY_VALUE_TO_HIDE_FIELD\"",
    "PageDisplayOrder": 1,
    "PageFieldDisplayOrder": 99,
    "PageID": "1.0",
    "PageLabel": "Issue direction"
  },
  {
    "CaseEventID": "directionIssued",
    "CaseFieldID": "hasRepresentative",
    "CaseTypeID": "Benefit",
    "DisplayContext": "MANDATORY",
    "LiveFrom": "01/01/2018",
    "PageDisplayOrder": 1,
    "PageFieldDisplayOrder": 99,
    "PageID": "1.0",
    "FieldShowCondition": "confidentialityType=\"DUMMY_VALUE_TO_HIDE_FIELD\"",
    "PageLabel": "Issue direction"
  },
  {
    "CaseEventID": "directionIssued",
    "CaseFieldID": "hasOtherPartyRep",
    "CaseTypeID": "Benefit",
    "DisplayContext": "MANDATORY",
    "LiveFrom": "01/01/2018",
    "PageDisplayOrder": 1,
    "PageFieldDisplayOrder": 99,
    "PageID": "1.0",
    "FieldShowCondition": "confidentialityType=\"DUMMY_VALUE_TO_HIDE_FIELD\"",
    "PageLabel": "Issue direction"
  },
  {
    "CaseEventID": "directionIssued",
    "CaseFieldID": "hasOtherPartyAppointee",
    "CaseTypeID": "Benefit",
    "DisplayContext": "MANDATORY",
    "LiveFrom": "01/01/2018",
    "PageDisplayOrder": 1,
    "PageFieldDisplayOrder": 99,
    "PageID": "1.0",
    "FieldShowCondition": "confidentialityType=\"DUMMY_VALUE_TO_HIDE_FIELD\"",
    "PageLabel": "Issue direction"
  },
  {
    "CaseEventID": "directionIssued",
    "CaseFieldID": "hasOtherParties",
    "CaseTypeID": "Benefit",
    "DisplayContext": "MANDATORY",
    "LiveFrom": "01/01/2018",
    "PageDisplayOrder": 1,
    "PageFieldDisplayOrder": 99,
    "PageID": "1.0",
    "FieldShowCondition": "confidentialityType=\"DUMMY_VALUE_TO_HIDE_FIELD\"",
    "PageLabel": "Issue direction"
  },
  {
    "CaseEventID": "directionIssued",
    "CaseFieldID": "hasJointParty",
    "CaseTypeID": "Benefit",
    "DisplayContext": "MANDATORY",
    "LiveFrom": "01/01/2018",
    "PageDisplayOrder": 1,
    "PageFieldDisplayOrder": 99,
    "PageID": "1.0",
    "FieldShowCondition": "confidentialityType=\"DUMMY_VALUE_TO_HIDE_FIELD\"",
    "PageLabel": "Issue direction"
  },
  {
    "CaseEventID": "directionIssued",
    "CaseFieldID": "selectPartiesDirectionsNotice",
    "CaseTypeID": "Benefit",
    "DisplayContext": "READONLY",
    "FieldShowCondition": "confidentialityType=\"confidential\"",
    "LiveFrom": "01/01/2018",
    "PageDisplayOrder": 1,
    "PageFieldDisplayOrder": 3,
    "PageID": "1.0",
    "PageLabel": "Issue direction"
  },
  {
    "CaseEventID": "directionIssued",
    "CaseFieldID": "sendDirectionNoticeToFTA",
    "CaseTypeID": "Benefit",
    "DisplayContext": "MANDATORY",
    "FieldShowCondition": "confidentialityType=\"confidential\"",
    "LiveFrom": "01/01/2018",
    "PageDisplayOrder": 1,
    "PageFieldDisplayOrder": 4,
    "PageID": "1.0",
    "PageLabel": "Issue direction",
    "RetainHiddenValue": "Yes"
  },
  {
    "CaseEventID": "directionIssued",
    "CaseFieldID": "sendDirectionNoticeToRepresentative",
    "CaseTypeID": "Benefit",
    "DisplayContext": "MANDATORY",
    "FieldShowCondition": "confidentialityType=\"confidential\" AND hasRepresentative = \"Yes\"",
    "LiveFrom": "01/01/2018",
    "PageDisplayOrder": 1,
    "PageFieldDisplayOrder": 5,
    "PageID": "1.0",
    "PageLabel": "Issue direction",
    "RetainHiddenValue": "Yes"
  },
  {
    "CaseEventID": "directionIssued",
    "CaseFieldID": "sendDirectionNoticeToOtherPartyRep",
    "CaseTypeID": "Benefit",
    "DisplayContext": "MANDATORY",
    "FieldShowCondition": "confidentialityType=\"confidential\" AND hasOtherPartyRep = \"Yes\"",
    "LiveFrom": "01/01/2018",
    "PageDisplayOrder": 1,
    "PageFieldDisplayOrder": 6,
    "PageID": "1.0",
    "PageLabel": "Issue direction",
    "RetainHiddenValue": "Yes"
  },
  {
    "CaseEventID": "directionIssued",
    "CaseFieldID": "sendDirectionNoticeToOtherPartyAppointee",
    "CaseTypeID": "Benefit",
    "DisplayContext": "MANDATORY",
    "FieldShowCondition": "confidentialityType=\"confidential\" AND hasOtherPartyAppointee = \"Yes\"",
    "LiveFrom": "01/01/2018",
    "PageDisplayOrder": 1,
    "PageFieldDisplayOrder": 7,
    "PageID": "1.0",
    "PageLabel": "Issue direction",
    "RetainHiddenValue": "Yes"
  },
  {
    "CaseEventID": "directionIssued",
    "CaseFieldID": "sendDirectionNoticeToOtherParty",
    "CaseTypeID": "Benefit",
    "DisplayContext": "MANDATORY",
    "FieldShowCondition": "confidentialityType=\"confidential\" AND hasOtherParties = \"Yes\"",
    "LiveFrom": "01/01/2018",
    "PageDisplayOrder": 1,
    "PageFieldDisplayOrder": 8,
    "PageID": "1.0",
    "PageLabel": "Issue direction",
    "RetainHiddenValue": "Yes"
  },
  {
    "CaseEventID": "directionIssued",
    "CaseFieldID": "sendDirectionNoticeToJointParty",
    "CaseTypeID": "Benefit",
    "DisplayContext": "MANDATORY",
    "FieldShowCondition": "confidentialityType=\"confidential\" AND hasJointParty = \"Yes\"",
    "LiveFrom": "01/01/2018",
    "PageDisplayOrder": 1,
    "PageFieldDisplayOrder": 9,
    "PageID": "1.0",
    "PageLabel": "Issue direction",
    "RetainHiddenValue": "Yes"
  },
  {
    "CaseEventID": "directionIssued",
    "CaseFieldID": "sendDirectionNoticeToAppellantOrAppointee",
    "CaseTypeID": "Benefit",
    "DisplayContext": "MANDATORY",
    "FieldShowCondition": "confidentialityType=\"confidential\"",
    "LiveFrom": "01/01/2018",
    "PageDisplayOrder": 1,
    "PageFieldDisplayOrder": 10,
    "PageID": "1.0",
    "PageLabel": "Issue direction",
    "RetainHiddenValue": "Yes"
  },
  {
    "CaseEventID": "directionIssued",
    "CaseFieldID": "directionDueDate",
    "CaseTypeID": "Benefit",
    "DisplayContext": "OPTIONAL",
    "FieldShowCondition": "directionTypeDl!=\"refuseExtension\" AND directionTypeDl!=\"refuseHearingRecordingRequest\"",
    "LiveFrom": "01/01/2018",
    "PageDisplayOrder": 1,
    "PageFieldDisplayOrder": 11,
    "PageID": "1.0",
    "PageLabel": "Issue direction",
    "RetainHiddenValue": "Yes"
  },
  {
    "LiveFrom": "06/10/2022",
    "CaseEventID": "directionIssued",
    "CaseFieldID": "tribunalDirectPoToAttend",
    "CaseTypeID": "Benefit",
    "DisplayContext": "OPTIONAL",
    "FieldShowCondition": "hearingRoute=\"listAssist\"",
    "PageDisplayOrder": 1,
    "PageFieldDisplayOrder": 12,
    "PageID": "1.0",
    "PageLabel": "Issue direction"
  },
  {
    "CaseEventID": "directionIssued",
    "CaseFieldID": "reservedToJudgeInterloc",
    "CaseTypeID": "Benefit",
    "DisplayContext": "OPTIONAL",
    "LiveFrom": "01/01/2018",
    "PageDisplayOrder": 1,
    "PageFieldDisplayOrder": 13,
    "PageID": "1.0",
    "PageLabel": "Issue direction",
    "ShowSummaryChangeOption": "Y"
  },
  {
    "CaseEventID": "directionIssued",
    "CaseFieldID": "createdInGapsFrom",
    "CaseTypeID": "Benefit",
    "DisplayContext": "MANDATORY",
    "FieldShowCondition": "bodyContent=\"doNotUse\"",
    "LiveFrom": "01/01/2018",
    "PageDisplayOrder": 1,
    "PageFieldDisplayOrder": 14,
    "PageID": "1.0",
    "PageLabel": "Issue direction",
    "RetainHiddenValue": "Yes"
  },
  {
    "CaseEventID": "directionIssued",
    "CaseFieldID": "documentSentToDwp",
    "CaseTypeID": "Benefit",
    "DisplayContext": "OPTIONAL",
    "FieldShowCondition": "createdInGapsFrom!=\"readyToList\"",
    "LiveFrom": "01/01/2018",
    "PageDisplayOrder": 1,
    "PageFieldDisplayOrder": 15,
    "PageID": "1.0",
    "PageLabel": "Issue direction"
  },
  {
    "CaseEventID": "directionIssued",
    "CaseFieldID": "extensionNextEventDl",
    "CaseTypeID": "Benefit",
    "DisplayContext": "MANDATORY",
    "FieldShowCondition": "directionTypeDl=\"refuseExtension\"",
    "LiveFrom": "01/01/2018",
    "PageDisplayOrder": 1,
    "PageFieldDisplayOrder": 16,
    "PageID": "1.0",
    "PageLabel": "Issue direction"
  },
  {
    "CaseEventID": "directionIssued",
    "CaseFieldID": "generateNotice",
    "CaseTypeID": "Benefit",
    "DisplayContext": "MANDATORY",
    "LiveFrom": "01/01/2018",
    "PageDisplayOrder": 1,
    "PageFieldDisplayOrder": 17,
    "PageID": "1.0",
    "PageLabel": "Issue direction"
  },
  {
    "CallBackURLMidEvent": "${CCD_DEF_TRIBUNALS_API_URL}/ccdMidEvent",
    "CaseEventID": "directionIssued",
    "CaseFieldID": "sscsInterlocDirectionDocument",
    "CaseTypeID": "Benefit",
    "DisplayContext": "OPTIONAL",
    "FieldShowCondition": "generateNotice=\"No\"",
    "LiveFrom": "01/01/2018",
    "PageDisplayOrder": 1,
    "PageFieldDisplayOrder": 18,
    "PageID": "1.0",
    "PageLabel": "Issue direction"
  },
  {
    "CaseEventID": "directionIssued",
    "CaseFieldID": "bodyContent",
    "CaseTypeID": "Benefit",
    "DisplayContext": "MANDATORY",
    "FieldShowCondition": "generateNotice=\"Yes\"",
    "LiveFrom": "01/01/2018",
    "PageDisplayOrder": 1,
    "PageFieldDisplayOrder": 19,
    "PageID": "1.0",
    "PageLabel": "Issue direction"
  },
  {
    "CaseEventID": "directionIssued",
    "CaseFieldID": "signedBy",
    "CaseTypeID": "Benefit",
    "DisplayContext": "MANDATORY",
    "FieldShowCondition": "generateNotice=\"Yes\"",
    "LiveFrom": "01/01/2018",
    "PageDisplayOrder": 1,
    "PageFieldDisplayOrder": 20,
    "PageID": "1.0",
    "PageLabel": "Issue direction"
  },
  {
    "CaseEventID": "directionIssued",
    "CaseFieldID": "signedRole",
    "CaseTypeID": "Benefit",
    "DisplayContext": "MANDATORY",
    "FieldShowCondition": "generateNotice=\"Yes\"",
    "LiveFrom": "01/01/2018",
    "PageDisplayOrder": 1,
    "PageFieldDisplayOrder": 21,
    "PageID": "1.0",
    "PageLabel": "Issue direction"
  },
  {
    "CallBackURLMidEvent": "${CCD_DEF_TRIBUNALS_API_URL}/ccdMidEvent",
    "CaseEventID": "directionIssued",
    "CaseFieldID": "dateAdded",
    "CaseTypeID": "Benefit",
    "DisplayContext": "OPTIONAL",
    "FieldShowCondition": "generateNotice=\"Yes\"",
    "LiveFrom": "01/01/2018",
    "PageDisplayOrder": 1,
    "PageFieldDisplayOrder": 22,
    "PageID": "1.0",
    "PageLabel": "Issue direction"
  },
  {
    "CaseEventID": "directionIssued",
    "CaseFieldID": "previewDocument",
    "CaseTypeID": "Benefit",
    "DisplayContext": "OPTIONAL",
    "LiveFrom": "01/01/2018",
    "PageDisplayOrder": 2,
    "PageFieldDisplayOrder": 23,
    "PageID": "2.0",
    "PageLabel": "Issue direction",
    "PageShowCondition": "generateNotice=\"Yes\""
  }
]
